setup.cfg
setup.py
py_protocols/__init__.py
py_protocols/protocols.py
py_protocols.egg-info/PKG-INFO
py_protocols.egg-info/SOURCES.txt
py_protocols.egg-info/dependency_links.txt
py_protocols.egg-info/top_level.txt