Metadata-Version: 1.1
Name: py-protocols
Version: 1.0.0
Summary: Absraction separation tool for python. Inspired by clojure protocols
Home-page: https://github.com/villlem/py-protocols
Author: Vojta Orgon
Author-email: villlem@gmail.com
License: MIT
Platform: UNKNOWN
Classifier: Intended Audience :: Developers
Classifier: License :: OSI Approved :: MIT License
Classifier: Operating System :: OS Independent
Classifier: Programming Language :: Python
